altscore/__init__.py
altscore/exceptions.py
altscore/altdata/__init__.py
altscore/altdata/helpers/__init__.py
altscore/altdata/model/__init__.py
altscore/altdata/model/batch.py
altscore/altdata/model/common_schemas.py
altscore/altdata/model/data_request.py
altscore/altdata/schemas/__init__.py
altscore/altdata/utils/__init__.py
altscore/altdata/utils/dataframes.py
altscore/borrower_central/__init__.py
altscore/borrower_central/utils.py
altscore/borrower_central/helpers/__init__.py
altscore/borrower_central/model/__init__.py
altscore/borrower_central/model/accounting_amount.py
altscore/borrower_central/model/accounting_documents.py
altscore/borrower_central/model/accounting_line_items.py
altscore/borrower_central/model/actionables.py
altscore/borrower_central/model/addresses.py
altscore/borrower_central/model/analytics.py
altscore/borrower_central/model/api_request.py
altscore/borrower_central/model/asset_fields.py
altscore/borrower_central/model/assets.py
altscore/borrower_central/model/attachments.py
altscore/borrower_central/model/authorizations.py
altscore/borrower_central/model/automations.py
altscore/borrower_central/model/bank_account_balances.py
altscore/borrower_central/model/bank_accounts.py
altscore/borrower_central/model/bank_transactions.py
altscore/borrower_central/model/borrower.py
altscore/borrower_central/model/borrower_fields.py
altscore/borrower_central/model/category.py
altscore/borrower_central/model/cms_settings.py
altscore/borrower_central/model/conversational_channel_connectors.py
altscore/borrower_central/model/conversational_conversations.py
altscore/borrower_central/model/conversational_messages.py
altscore/borrower_central/model/conversational_templates.py
altscore/borrower_central/model/custom_reports.py
altscore/borrower_central/model/data_models.py
altscore/borrower_central/model/deal_contacts.py
altscore/borrower_central/model/deal_fields.py
altscore/borrower_central/model/deal_steps.py
altscore/borrower_central/model/deals.py
altscore-0.1.251.dist-info/licenses/LICENSE
altscore-0.1.251.dist-info/METADATA
altscore-0.1.251.dist-info/WHEEL
altscore-0.1.251.dist-info/top_level.txt
altscore-0.1.251.dist-info/RECORD
