Metadata-Version: 2.4
Name: altscore
Version: 0.1.251
Summary: Python SDK for AltScore. It provides a simple interface to the AltScore API.
Home-page: https://github.com/altscore/altscore-python
Author: AltScore
Author-email: developers@altscore.ai
License: MIT
Classifier: Intended Audience :: Developers
Classifier: License :: OSI Approved :: MIT License
Classifier: Operating System :: OS Independent
Requires-Python: >=3.8
License-File: LICENSE
Requires-Dist: loguru
Requires-Dist: click
Requires-Dist: requests
Requires-Dist: pydantic==1.10.13
Requires-Dist: httpx
Requires-Dist: stringcase
Requires-Dist: python-decouple
Requires-Dist: python-dateutil==2.8.2
Requires-Dist: pyjwt
Requires-Dist: fuzzywuzzy~=0.18.0
Requires-Dist: python-Levenshtein<=0.26.1
Requires-Dist: aiofiles==24.1.0
Requires-Dist: pydantic[email]
Provides-Extra: dev
Requires-Dist: pytest>=7.0; extra == "dev"
Requires-Dist: twine>=4.0.2; extra == "dev"
Requires-Dist: pandas; extra == "dev"
Requires-Dist: tabulate; extra == "dev"
Provides-Extra: data-tools
Requires-Dist: pandas; extra == "data-tools"
Requires-Dist: tabulate; extra == "data-tools"
Dynamic: author
Dynamic: author-email
Dynamic: classifier
Dynamic: description
Dynamic: description-content-type
Dynamic: home-page
Dynamic: license
Dynamic: license-file
Dynamic: provides-extra
Dynamic: requires-dist
Dynamic: requires-python
Dynamic: summary
